solidspy/__init__.py
solidspy/__main__.py
solidspy/assemutil.py
solidspy/femutil.py
solidspy/gaussutil.py
solidspy/postprocesor.py
solidspy/preprocesor.py
solidspy/solids_GUI.py
solidspy/solutil.py
solidspy/uelutil.py
solidspy-1.0.16.dist-info/METADATA
solidspy-1.0.16.dist-info/RECORD
solidspy-1.0.16.dist-info/WHEEL
solidspy-1.0.16.dist-info/entry_points.txt
solidspy-1.0.16.dist-info/top_level.txt
