Metadata-Version: 2.1
Name: solidspy
Version: 1.0.16
Summary: A simple Finite Element program
Home-page: https://github.com/AppliedMechanics-EAFIT/SolidsPy
Author: Juan Gomez <jgomezc1@eafit.edu.co>, Nicolas Guarin-Zapata <nicoguarin@gmail.com>
Author-email: jgomezc1@eafit.edu.co
License: MIT
Keywords: finite-elements fem scientific-computing
Platform: UNKNOWN
Classifier: Development Status :: 3 - Alpha
Classifier: Intended Audience :: Education
Classifier: Topic :: Scientific/Engineering
Classifier: License :: OSI Approved :: MIT License
Classifier: Programming Language :: Python :: 2
Classifier: Programming Language :: Python :: 2.7
Classifier: Programming Language :: Python :: 3
Requires-Dist: numpy
Requires-Dist: scipy
Requires-Dist: matplotlib
Requires-Dist: easygui
Requires-Dist: meshio
